{
  "version": "1.1.63",
  "package_url": "https://github.com/Toi uu chay song song TikTok Workflow theo nhieu tai khoan Grok/releases/download/v1.1.63/FlowTool_v1.1.63.zip",
  "sha256": "f0b152154f107574a564deb7fdaf07178388bae620a3a1436542172562d43f37",
  "notes": "Cap nhat FlowTool",
  "published_at": "2026-05-16T11:29:01Z",
  "full_package_url": "https://github.com/Toi uu chay song song TikTok Workflow theo nhieu tai khoan Grok/releases/download/v1.1.63/FlowTool_FULL_v1.1.63.zip",
  "full_sha256": "3020ee9019b3214c981461fdf2db5dcd5da20de985c815645c9c486d0eec1cf4"
}